kcntools/__init__.py
kcntools/chutils.py
kcntools/darray.py
kcntools/darts.py
kcntools/strutils.py
kcntools/timefmt.py
kcntools/Sentence_similarity/__init__.py
kcntools/Sentence_similarity/constants.py
kcntools/Sentence_similarity/entity_extractor.py
kcntools/Sentence_similarity/qzhou_stopwords.txt
kcntools/Sentence_similarity/sentence_similarity.py
kcntools-1.0.2.data/data/my_data/tmpl
kcntools-1.0.2.dist-info/licenses/LICENSE
kcntools-1.0.2.dist-info/METADATA
kcntools-1.0.2.dist-info/WHEEL
kcntools-1.0.2.dist-info/entry_points.txt
kcntools-1.0.2.dist-info/top_level.txt
kcntools-1.0.2.dist-info/RECORD
