Metadata-Version: 2.4
Name: kcntools
Version: 1.0.2
Summary: kc ai nlp tools
Home-page: https://ezone.ksyun.com/code/ai-app/kcntools/-/tree
Author: xuen
Author-email: xuen@kingsoft.com
Project-URL: Bug Reports, https://ezone.ksyun.com/code/ai-app/kcntools/-/tree
Keywords: machine-learning,deep-learning,ml,pytorch,YOLO,object-detection,YOLOv3,YOLOv4,YOLOv5
Classifier: Development Status :: 5 - Production/Stable
Classifier: Intended Audience :: Developers
Classifier: Operating System :: OS Independent
Classifier: Topic :: Education
Classifier: Topic :: Scientific/Engineering
Classifier: Topic :: Scientific/Engineering :: Artificial Intelligence
Classifier: Topic :: Scientific/Engineering :: Image Recognition
Classifier: License :: OSI Approved :: GNU General Public License v3 (GPLv3)
Classifier: Programming Language :: Python :: 3.7
Classifier: Programming Language :: Python :: 3.8
Classifier: Programming Language :: Python :: 3.9
Requires-Python: >=3.7, <4
License-File: LICENSE
Provides-Extra: dev
Requires-Dist: check-manifest; extra == "dev"
Provides-Extra: test
Requires-Dist: coverage; extra == "test"
Dynamic: author
Dynamic: author-email
Dynamic: classifier
Dynamic: description
Dynamic: description-content-type
Dynamic: home-page
Dynamic: keywords
Dynamic: license-file
Dynamic: project-url
Dynamic: provides-extra
Dynamic: requires-python
Dynamic: summary
